{"WUSTL":[{"Patient ID":"WUSTL 105",
"Gender":"F",
"Age":"49",
"Model ID":"WUSTL 105-07",
"Primary Site":"Colon",
"Sample Site":"Liver",
"Tumor Type":"Metastatic",
"Sample Type":"surgical sample",
"Histology":"Colorectal Adenocarcinoma",
"Clinical Diagnosis":"Colorectal Adenocarcinoma",
"Grades":"Not Specified",
"Stage":"Not Specified",
"Markers":"",
"Treatment Naive":"Not Specified",
"Strain":"NOD.CB17-Prkdcscid/J",
"Tumor Prep":"tumor solid",
"Engraftment Site":"Sub-cutaneous;  dorsal flank"
},
{"Patient ID":"WUSTL 116",
"Gender":"M",
"Age":"48",
"Model ID":"WUSTL 116-07",
"Primary Site":"Rectosigmoid Colon",
"Sample Site":"Liver",
"Tumor Type":"Metastatic",
"Sample Type":"surgical sample",
"Histology":"Colorectal Adenocarcinoma",
"Clinical Diagnosis":"Colorectal Adenocarcinoma",
"Grades":"Not Specified",
"Stage":"Not Specified",
"Markers":"",
"Treatment Naive":"Not Specified",
"Strain":"NOD.CB17-Prkdcscid/J",
"Tumor Prep":"tumor solid",
"Engraftment Site":"Sub-cutaneous;  dorsal flank"
},
{"Patient ID":"WUSTL 117",
"Gender":"M",
"Age":"71",
"Model ID":"WUSTL 117-06",
"Primary Site":"Head of the Pancreas",
"Sample Site":"Pancreas",
"Tumor Type":"Primary",
"Sample Type":"surgical sample",
"Histology":"Pancreatic Ductal Adenocarcinoma",
"Clinical Diagnosis":"Pancreatic Ductal Adenocarcinoma",
"Grades":"G2/G3",
"Stage":"pT3/N1/MX",
"Markers":"",
"Treatment Naive":"Not Specified",
"Strain":"NOD.CB17-Prkdcscid/J",
"Tumor Prep":"tumor solid",
"Engraftment Site":"Sub-cutaneous;  dorsal flank"
},
{"Patient ID":"WUSTL 121",
"Gender":"M",
"Age":"50",
"Model ID":"WUSTL 121-07",
"Primary Site":"Colon",
"Sample Site":"Liver",
"Tumor Type":"Metastatic",
"Sample Type":"surgical sample",
"Histology":"Colorectal Adenocarcinoma",
"Clinical Diagnosis":"Colorectal Adenocarcinoma",
"Grades":"Not Specified",
"Stage":"Not Specified",
"Markers":"",
"Treatment Naive":"Not Specified",
"Strain":"NOD.CB17-Prkdcscid/J",
"Tumor Prep":"tumor solid",
"Engraftment Site":"Sub-cutaneous;  dorsal flank"
},
{"Patient ID":"WUSTL 123",
"Gender":"F",
"Age":"50",
"Model ID":"WUSTL 123-08",
"Primary Site":"Skin",
"Sample Site":"Lung",
"Tumor Type":"Metastatic",
"Sample Type":"surgical sample",
"Histology":"Cutaneous Melanoma",
"Clinical Diagnosis":"Cutaneous Melanoma",
"Grades":"Not Specified",
"Stage":"Not Specified",
"Markers":"",
"Treatment Naive":"Not Specified",
"Strain":"NOD.CB17-Prkdcscid/J",
"Tumor Prep":"tumor solid",
"Engraftment Site":"Sub-cutaneous;  dorsal flank"
},
{"Patient ID":"WUSTL 129",
"Gender":"M",
"Age":"47",
"Model ID":"WUSTL 129-07",
"Primary Site":"Colon",
"Sample Site":"Liver",
"Tumor Type":"Metastatic",
"Sample Type":"surgical sample",
"Histology":"Colorectal Adenocarcinoma",
"Clinical Diagnosis":"Colorectal Adenocarcinoma",
"Grades":"G2/G3",
"Stage":"ypT3/N2a/M1a",
"Markers":"",
"Treatment Naive":"Not Specified",
"Strain":"NOD.CB17-Prkdcscid/J",
"Tumor Prep":"tumor solid",
"Engraftment Site":"Sub-cutaneous;  dorsal flank"
},
{"Patient ID":"WUSTL 139",
"Gender":"M",
"Age":"70",
"Model ID":"WUSTL 139-07",
"Primary Site":"Skin",
"Sample Site":"Skin",
"Tumor Type":"Metastatic",
"Sample Type":"surgical sample",
"Histology":"Cutaneous Melanoma",
"Clinical Diagnosis":"Cutaneous Melanoma",
"Grades":"G1",
"Stage":"Not Specified",
"Markers":"",
"Treatment Naive":"Not Specified",
"Strain":"NOD.CB17-Prkdcscid/J",
"Tumor Prep":"tumor solid",
"Engraftment Site":"Sub-cutaneous;  dorsal flank"
},
{"Patient ID":"WUSTL 148",
"Gender":"M",
"Age":"59",
"Model ID":"WUSTL 148-06",
"Primary Site":"Sigmoid Colon",
"Sample Site":"Colon",
"Tumor Type":"Primary",
"Sample Type":"surgical sample",
"Histology":"Colorectal Adenocarcinoma",
"Clinical Diagnosis":"Colorectal Adenocarcinoma",
"Grades":"G2/G3",
"Stage":"pT3/N1a/MX",
"Markers":"",
"Treatment Naive":"Not Specified",
"Strain":"NOD.CB17-Prkdcscid/J",
"Tumor Prep":"tumor solid",
"Engraftment Site":"Sub-cutaneous;  dorsal flank"
},
{"Patient ID":"WUSTL 150",
"Gender":"M",
"Age":"67",
"Model ID":"WUSTL 150-07",
"Primary Site":"Colon",
"Sample Site":"Liver",
"Tumor Type":"Metastatic",
"Sample Type":"surgical sample",
"Histology":"Colorectal Adenocarcinoma",
"Clinical Diagnosis":"Colorectal Adenocarcinoma",
"Grades":"Not Specified",
"Stage":"Not Specified",
"Markers":"",
"Treatment Naive":"Not Specified",
"Strain":"NOD.CB17-Prkdcscid/J",
"Tumor Prep":"tumor solid",
"Engraftment Site":"Sub-cutaneous;  dorsal flank"
},
{"Patient ID":"WUSTL 158",
"Gender":"F",
"Age":"44",
"Model ID":"WUSTL 158-07",
"Primary Site":"Colon",
"Sample Site":"Liver",
"Tumor Type":"Metastatic",
"Sample Type":"surgical sample",
"Histology":"Colorectal Adenocarcinoma",
"Clinical Diagnosis":"Colorectal Adenocarcinoma",
"Grades":"G2",
"Stage":"ypT2/N1a/MX",
"Markers":"",
"Treatment Naive":"Not Specified",
"Strain":"NOD.CB17-Prkdcscid/J",
"Tumor Prep":"tumor solid",
"Engraftment Site":"Sub-cutaneous;  dorsal flank"
},
{"Patient ID":"WUSTL 159",
"Gender":"F",
"Age":"62",
"Model ID":"WUSTL 159-07",
"Primary Site":"Skin",
"Sample Site":"Upper Limb NOS",
"Tumor Type":"Metastatic",
"Sample Type":"surgical sample",
"Histology":"Cutaneous Melanoma",
"Clinical Diagnosis":"Cutaneous Melanoma",
"Grades":"Not Specified",
"Stage":"pTx/pNx",
"Markers":"",
"Treatment Naive":"Not Specified",
"Strain":"NOD.CB17-Prkdcscid/J",
"Tumor Prep":"tumor solid",
"Engraftment Site":"Sub-cutaneous;  dorsal flank"
},
{"Patient ID":"WUSTL 162",
"Gender":"M",
"Age":"71",
"Model ID":"WUSTL 162-06",
"Primary Site":"Head of the Pancreas",
"Sample Site":"Pancreas",
"Tumor Type":"Primary",
"Sample Type":"surgical sample",
"Histology":"Pancreatic Ductal Adenocarcinoma",
"Clinical Diagnosis":"Pancreatic Ductal Adenocarcinoma",
"Grades":"G3",
"Stage":"pT3/N1/MX",
"Markers":"",
"Treatment Naive":"Not Specified",
"Strain":"NOD.CB17-Prkdcscid/J",
"Tumor Prep":"tumor solid",
"Engraftment Site":"Sub-cutaneous;  dorsal flank"
},
{"Patient ID":"WUSTL 167",
"Gender":"M",
"Age":"68",
"Model ID":"WUSTL 167-07",
"Primary Site":"Skin",
"Sample Site":"Small Intestine",
"Tumor Type":"Metastatic",
"Sample Type":"surgical sample",
"Histology":"Cutaneous Melanoma",
"Clinical Diagnosis":"Cutaneous Melanoma",
"Grades":"Not Specified",
"Stage":"Not Specified",
"Markers":"",
"Treatment Naive":"Not Specified",
"Strain":"NOD.CB17-Prkdcscid/J",
"Tumor Prep":"tumor solid",
"Engraftment Site":"Sub-cutaneous;  dorsal flank"
},
{"Patient ID":"WUSTL 174",
"Gender":"F",
"Age":"55",
"Model ID":"WUSTL 174-07",
"Primary Site":"Skin",
"Sample Site":"Gastric Peritoneal Noule",
"Tumor Type":"Metastatic",
"Sample Type":"surgical sample",
"Histology":"Cutaneous Melanoma",
"Clinical Diagnosis":"Cutaneous Melanoma",
"Grades":"G1",
"Stage":"Not Specified",
"Markers":"",
"Treatment Naive":"Not Specified",
"Strain":"NOD.CB17-Prkdcscid/J",
"Tumor Prep":"tumor solid",
"Engraftment Site":"Sub-cutaneous;  dorsal flank"
},
{"Patient ID":"WUSTL 175",
"Gender":"M",
"Age":"72",
"Model ID":"WUSTL 175-06",
"Primary Site":"Pancreas Head",
"Sample Site":"Pancreas",
"Tumor Type":"Primary",
"Sample Type":"surgical sample",
"Histology":"Pancreatic Adenocarcinoma",
"Clinical Diagnosis":"Pancreatic Adenocarcinoma",
"Grades":"G3",
"Stage":"pT3/N1/MX",
"Markers":"",
"Treatment Naive":"Not Specified",
"Strain":"NOD.CB17-Prkdcscid/J",
"Tumor Prep":"tumor solid",
"Engraftment Site":"Sub-cutaneous;  dorsal flank"
},
{"Patient ID":"WUSTL 185",
"Gender":"M",
"Age":"66",
"Model ID":"WUSTL 185-07",
"Primary Site":"Pancreas",
"Sample Site":"Abdominal Wall",
"Tumor Type":"Metastatic",
"Sample Type":"surgical sample",
"Histology":"Pancreatic Adenocarcinoma",
"Clinical Diagnosis":"Pancreatic Adenocarcinoma",
"Grades":"Not Specified",
"Stage":"Not Specified",
"Markers":"",
"Treatment Naive":"Not Specified",
"Strain":"NOD.CB17-Prkdcscid/J",
"Tumor Prep":"tumor solid",
"Engraftment Site":"Sub-cutaneous;  dorsal flank"
},
{"Patient ID":"WUSTL 186",
"Gender":"M",
"Age":"54",
"Model ID":"WUSTL 186-07",
"Primary Site":"Rectosigmoid Colon",
"Sample Site":"Liver",
"Tumor Type":"Metastatic",
"Sample Type":"surgical sample",
"Histology":"Colorectal Adenocarcinoma",
"Clinical Diagnosis":"Colorectal Adenocarcinoma",
"Grades":"G3",
"Stage":"yT3/N1c/MX",
"Markers":"",
"Treatment Naive":"Not Specified",
"Strain":"NOD.CB17-Prkdcscid/J",
"Tumor Prep":"tumor solid",
"Engraftment Site":"Sub-cutaneous;  dorsal flank"
},
{"Patient ID":"WUSTL 187",
"Gender":"M",
"Age":"63",
"Model ID":"WUSTL 187-07",
"Primary Site":"Skin",
"Sample Site":"Lower Back",
"Tumor Type":"Metastatic",
"Sample Type":"surgical sample",
"Histology":"Cutaneous Melanoma",
"Clinical Diagnosis":"Cutaneous Melanoma",
"Grades":"Not Specified",
"Stage":"T4/N3/MX",
"Markers":"",
"Treatment Naive":"Not Specified",
"Strain":"NOD.CB17-Prkdcscid/J",
"Tumor Prep":"tumor solid",
"Engraftment Site":"Sub-cutaneous;  dorsal flank"
},
{"Patient ID":"WUSTL 191",
"Gender":"M",
"Age":"60",
"Model ID":"WUSTL 191-06",
"Primary Site":"Rectum",
"Sample Site":"Rectum",
"Tumor Type":"Primary",
"Sample Type":"surgical sample",
"Histology":"Colorectal Adenocarcinoma",
"Clinical Diagnosis":"Colorectal Adenocarcinoma",
"Grades":"G2",
"Stage":"ypT3/N1b/M1b",
"Markers":"",
"Treatment Naive":"Not Specified",
"Strain":"NOD.CB17-Prkdcscid/J",
"Tumor Prep":"tumor solid",
"Engraftment Site":"Sub-cutaneous;  dorsal flank"
},
{"Patient ID":"WUSTL 191",
"Gender":"M",
"Age":"60",
"Model ID":"WUSTL 191-07",
"Primary Site":"Rectum",
"Sample Site":"Liver",
"Tumor Type":"Metastatic",
"Sample Type":"surgical sample",
"Histology":"Colorectal Adenocarcinoma",
"Clinical Diagnosis":"Colorectal Adenocarcinoma",
"Grades":"G2",
"Stage":"ypT3/N1b/M1b",
"Markers":"",
"Treatment Naive":"Not Specified",
"Strain":"NOD.CB17-Prkdcscid/J",
"Tumor Prep":"tumor solid",
"Engraftment Site":"Sub-cutaneous;  dorsal flank"
},
{"Patient ID":"WUSTL 200",
"Gender":"M",
"Age":"76",
"Model ID":"WUSTL 200-06",
"Primary Site":"Head of the Pancreas",
"Sample Site":"Pancreas",
"Tumor Type":"Primary",
"Sample Type":"surgical sample",
"Histology":"Pancreatic Ductal Adenocarcinoma",
"Clinical Diagnosis":"Pancreatic Ductal Adenocarcinoma",
"Grades":"G2/G3",
"Stage":"pT1/N1/MX",
"Markers":"",
"Treatment Naive":"Not Specified",
"Strain":"NOD.CB17-Prkdcscid/J",
"Tumor Prep":"tumor solid",
"Engraftment Site":"Sub-cutaneous;  dorsal flank"
},
{"Patient ID":"WUSTL 222",
"Gender":"M",
"Age":"55",
"Model ID":"WUSTL 222-06",
"Primary Site":"Body of the Pancreas",
"Sample Site":"Pancreas",
"Tumor Type":"Primary",
"Sample Type":"surgical sample",
"Histology":"Pancreatic Ductal Adenocarcinoma",
"Clinical Diagnosis":"Pancreatic Ductal Adenocarcinoma",
"Grades":"G3",
"Stage":"pT2/N1/MX",
"Markers":"",
"Treatment Naive":"Not Specified",
"Strain":"NOD.CB17-Prkdcscid/J",
"Tumor Prep":"tumor solid",
"Engraftment Site":"Sub-cutaneous;  dorsal flank"
},
{"Patient ID":"WUSTL 242",
"Gender":"F",
"Age":"70",
"Model ID":"WUSTL 242-06",
"Primary Site":"Head of the Pancreas",
"Sample Site":"Pancreas",
"Tumor Type":"Primary",
"Sample Type":"surgical sample",
"Histology":"Pancreatic Ductal Adenocarcinoma",
"Clinical Diagnosis":"Pancreatic Ductal Adenocarcinoma",
"Grades":"G2",
"Stage":"pT3/N1/MX",
"Markers":"",
"Treatment Naive":"Not Specified",
"Strain":"NOD.CB17-Prkdcscid/J",
"Tumor Prep":"tumor solid",
"Engraftment Site":"Sub-cutaneous;  dorsal flank"
},
{"Patient ID":"WUSTL 254",
"Gender":"F",
"Age":"74",
"Model ID":"WUSTL 254-06",
"Primary Site":"Body of the Pancreas",
"Sample Site":"Pancreas",
"Tumor Type":"Primary",
"Sample Type":"surgical sample",
"Histology":"Pancreatic Ductal Adenocarcinoma",
"Clinical Diagnosis":"Pancreatic Ductal Adenocarcinoma",
"Grades":"G2",
"Stage":"ypT3/N0/MX",
"Markers":"",
"Treatment Naive":"Not Specified",
"Strain":"NOD.CB17-Prkdcscid/J",
"Tumor Prep":"tumor solid",
"Engraftment Site":"Sub-cutaneous;  dorsal flank"
},
{"Patient ID":"WUSTL 266",
"Gender":"M",
"Age":"61",
"Model ID":"WUSTL 266-06",
"Primary Site":"Tail of the Pancreas",
"Sample Site":"Pancreas",
"Tumor Type":"Primary",
"Sample Type":"surgical sample",
"Histology":"Pancreatic Ductal Adenocarcinoma",
"Clinical Diagnosis":"Pancreatic Ductal Adenocarcinoma",
"Grades":"G3",
"Stage":"pT3/N0/M0",
"Markers":"",
"Treatment Naive":"Not Specified",
"Strain":"NOD.CB17-Prkdcscid/J",
"Tumor Prep":"tumor solid",
"Engraftment Site":"Sub-cutaneous;  dorsal flank"
},
{"Patient ID":"WUSTL 268",
"Gender":"M",
"Age":"60",
"Model ID":"WUSTL 268-06",
"Primary Site":"Colon",
"Sample Site":"Colon",
"Tumor Type":"Primary",
"Sample Type":"surgical sample",
"Histology":"Colorectal Adenocarcinoma",
"Clinical Diagnosis":"Colorectal Adenocarcinoma",
"Grades":"G2",
"Stage":"pT3/N1a/M1a",
"Markers":"",
"Treatment Naive":"Not Specified",
"Strain":"NOD.CB17-Prkdcscid/J",
"Tumor Prep":"tumor solid",
"Engraftment Site":"Sub-cutaneous;  dorsal flank"
},
{"Patient ID":"WUSTL 268",
"Gender":"M",
"Age":"60",
"Model ID":"WUSTL 268-07",
"Primary Site":"Colon",
"Sample Site":"Liver",
"Tumor Type":"Metastatic",
"Sample Type":"surgical sample",
"Histology":"Colorectal Adenocarcinoma",
"Clinical Diagnosis":"Colorectal Adenocarcinoma",
"Grades":"G2",
"Stage":"pT3/N1a/M1a",
"Markers":"",
"Treatment Naive":"Not Specified",
"Strain":"NOD.CB17-Prkdcscid/J",
"Tumor Prep":"tumor solid",
"Engraftment Site":"Sub-cutaneous;  dorsal flank"
},
{"Patient ID":"WUSTL 277",
"Gender":"M",
"Age":"73",
"Model ID":"WUSTL 277-06",
"Primary Site":"Head of the Pancreas",
"Sample Site":"Pancreas",
"Tumor Type":"Primary",
"Sample Type":"surgical sample",
"Histology":"Pancreatic Ductal Adenocarcinoma",
"Clinical Diagnosis":"Pancreatic Ductal Adenocarcinoma",
"Grades":"G3",
"Stage":"p3/N0/M0",
"Markers":"",
"Treatment Naive":"Not Specified",
"Strain":"NOD.CB17-Prkdcscid/J",
"Tumor Prep":"tumor solid",
"Engraftment Site":"Sub-cutaneous;  dorsal flank"
},
{"Patient ID":"WUSTL 287",
"Gender":"F",
"Age":"62",
"Model ID":"WUSTL 287-06",
"Primary Site":"Colon",
"Sample Site":"Colon",
"Tumor Type":"Primary",
"Sample Type":"surgical sample",
"Histology":"Colorectal Adenocarcinoma",
"Clinical Diagnosis":"Colorectal Adenocarcinoma",
"Grades":"G2",
"Stage":"pT2/N1a/M1a",
"Markers":"",
"Treatment Naive":"Not Specified",
"Strain":"NOD.CB17-Prkdcscid/J",
"Tumor Prep":"tumor solid",
"Engraftment Site":"Sub-cutaneous;  dorsal flank"
},
{"Patient ID":"WUSTL 287",
"Gender":"F",
"Age":"62",
"Model ID":"WUSTL 287-07",
"Primary Site":"Colon",
"Sample Site":"Liver",
"Tumor Type":"Metastatic",
"Sample Type":"surgical sample",
"Histology":"Colorectal Adenocarcinoma",
"Clinical Diagnosis":"Colorectal Adenocarcinoma",
"Grades":"G2",
"Stage":"pT2/N1a/M1a",
"Markers":"",
"Treatment Naive":"Not Specified",
"Strain":"NOD.CB17-Prkdcscid/J",
"Tumor Prep":"tumor solid",
"Engraftment Site":"Sub-cutaneous;  dorsal flank"
},
{"Patient ID":"WUSTL 292",
"Gender":"M",
"Age":"45",
"Model ID":"WUSTL 292-06",
"Primary Site":"Rectum",
"Sample Site":"Rectum",
"Tumor Type":"Primary",
"Sample Type":"surgical sample",
"Histology":"Colorectal Adenocarcinoma",
"Clinical Diagnosis":"Colorectal Adenocarcinoma",
"Grades":"G2/G3",
"Stage":"pT3/N1b/M1a",
"Markers":"",
"Treatment Naive":"Not Specified",
"Strain":"NOD.CB17-Prkdcscid/J",
"Tumor Prep":"tumor solid",
"Engraftment Site":"Sub-cutaneous;  dorsal flank"
},
{"Patient ID":"WUSTL 292 [2]",
"Gender":"M",
"Age":"46",
"Model ID":"WUSTL 292 [2]-07",
"Primary Site":"Rectum",
"Sample Site":"Liver",
"Tumor Type":"Metastatic",
"Sample Type":"surgical sample",
"Histology":"Colorectal Adenocarcinoma",
"Clinical Diagnosis":"Colorectal Adenocarcinoma",
"Grades":"G2/G3",
"Stage":"pT3/N1b/M1a",
"Markers":"",
"Treatment Naive":"Not Specified",
"Strain":"NOD.CB17-Prkdcscid/J",
"Tumor Prep":"tumor solid",
"Engraftment Site":"Sub-cutaneous;  dorsal flank"
},
{"Patient ID":"WUSTL 299",
"Gender":"M",
"Age":"86",
"Model ID":"WUSTL 299-06",
"Primary Site":"Colon",
"Sample Site":"Colon",
"Tumor Type":"Primary",
"Sample Type":"surgical sample",
"Histology":"Colorectal Adenocarcinoma",
"Clinical Diagnosis":"Colorectal Adenocarcinoma",
"Grades":"G2/G3",
"Stage":"pT3/N0/MX",
"Markers":"",
"Treatment Naive":"Not Specified",
"Strain":"NOD.CB17-Prkdcscid/J",
"Tumor Prep":"tumor solid",
"Engraftment Site":"Sub-cutaneous;  dorsal flank"
},
{"Patient ID":"WUSTL 301",
"Gender":"M",
"Age":"46",
"Model ID":"WUSTL 301-07",
"Primary Site":"Colon",
"Sample Site":"Liver",
"Tumor Type":"Metastatic",
"Sample Type":"surgical sample",
"Histology":"Colorectal Adenocarcinoma",
"Clinical Diagnosis":"Colorectal Adenocarcinoma",
"Grades":"GX",
"Stage":"ypT3/N2b/M1a",
"Markers":"",
"Treatment Naive":"Not Specified",
"Strain":"NOD.CB17-Prkdcscid/J",
"Tumor Prep":"tumor solid",
"Engraftment Site":"Sub-cutaneous;  dorsal flank"
},
{"Patient ID":"WUSTL 315",
"Gender":"M",
"Age":"49",
"Model ID":"WUSTL 315-07",
"Primary Site":"Colon",
"Sample Site":"Liver",
"Tumor Type":"Metastatic",
"Sample Type":"surgical sample",
"Histology":"Colorectal Adenocarcinoma",
"Clinical Diagnosis":"Colorectal Adenocarcinoma",
"Grades":"Not Specified",
"Stage":"Not Specified",
"Markers":"",
"Treatment Naive":"Not Specified",
"Strain":"NOD.CB17-Prkdcscid/J",
"Tumor Prep":"tumor solid",
"Engraftment Site":"Sub-cutaneous;  dorsal flank"
},
{"Patient ID":"WUSTL 318",
"Gender":"M",
"Age":"77",
"Model ID":"WUSTL 318-06",
"Primary Site":"Rectum",
"Sample Site":"Rectum",
"Tumor Type":"Primary",
"Sample Type":"surgical sample",
"Histology":"Colorectal Adenocarcinoma",
"Clinical Diagnosis":"Colorectal Adenocarcinoma",
"Grades":"G2",
"Stage":"pT3/N0/MX",
"Markers":"",
"Treatment Naive":"Not Specified",
"Strain":"NOD.CB17-Prkdcscid/J",
"Tumor Prep":"tumor solid",
"Engraftment Site":"Sub-cutaneous;  dorsal flank"
},
{"Patient ID":"WUSTL 322",
"Gender":"M",
"Age":"42",
"Model ID":"WUSTL 322-06",
"Primary Site":"Rectosigmoid Colon",
"Sample Site":"Colon",
"Tumor Type":"Primary",
"Sample Type":"surgical sample",
"Histology":"Colorectal Adenocarcinoma",
"Clinical Diagnosis":"Colorectal Adenocarcinoma",
"Grades":"G2/G3",
"Stage":"yTpT3/N1c/M1b",
"Markers":"",
"Treatment Naive":"Not Specified",
"Strain":"NOD.CB17-Prkdcscid/J",
"Tumor Prep":"tumor solid",
"Engraftment Site":"Sub-cutaneous;  dorsal flank"
},
{"Patient ID":"WUSTL 322",
"Gender":"M",
"Age":"42",
"Model ID":"WUSTL 322-07",
"Primary Site":"Rectosigmoid Colon",
"Sample Site":"Liver",
"Tumor Type":"Metastatic",
"Sample Type":"surgical sample",
"Histology":"Colorectal Adenocarcinoma",
"Clinical Diagnosis":"Colorectal Adenocarcinoma",
"Grades":"G2/G3",
"Stage":"yTpT3/N1c/M1b",
"Markers":"",
"Treatment Naive":"Not Specified",
"Strain":"NOD.CB17-Prkdcscid/J",
"Tumor Prep":"tumor solid",
"Engraftment Site":"Sub-cutaneous;  dorsal flank"
},
{"Patient ID":"WUSTL 324",
"Gender":"M",
"Age":"51",
"Model ID":"WUSTL 324-06",
"Primary Site":"Colon",
"Sample Site":"Colon",
"Tumor Type":"Primary",
"Sample Type":"surgical sample",
"Histology":"Colorectal Adenocarcinoma",
"Clinical Diagnosis":"Colorectal Adenocarcinoma",
"Grades":"G2",
"Stage":"pT2/N0/MX",
"Markers":"",
"Treatment Naive":"Not Specified",
"Strain":"NOD.CB17-Prkdcscid/J",
"Tumor Prep":"tumor solid",
"Engraftment Site":"Sub-cutaneous;  dorsal flank"
},
{"Patient ID":"WUSTL 329",
"Gender":"F",
"Age":"53",
"Model ID":"WUSTL 329-06",
"Primary Site":"Colon",
"Sample Site":"Colon",
"Tumor Type":"Primary",
"Sample Type":"surgical sample",
"Histology":"Colorectal Adenocarcinoma",
"Clinical Diagnosis":"Colorectal Adenocarcinoma",
"Grades":"G2",
"Stage":"T3/N0/MX",
"Markers":"",
"Treatment Naive":"Not Specified",
"Strain":"NOD.CB17-Prkdcscid/J",
"Tumor Prep":"tumor solid",
"Engraftment Site":"Sub-cutaneous;  dorsal flank"
},
{"Patient ID":"WUSTL 334",
"Gender":"M",
"Age":"72",
"Model ID":"WUSTL 334-06",
"Primary Site":"Head of the Pancreas",
"Sample Site":"Pancreas",
"Tumor Type":"Primary",
"Sample Type":"surgical sample",
"Histology":"Pancreatic Ductal Adenocarcinoma",
"Clinical Diagnosis":"Pancreatic Ductal Adenocarcinoma",
"Grades":"G3",
"Stage":"pT3/N1/M1",
"Markers":"",
"Treatment Naive":"Not Specified",
"Strain":"NOD.CB17-Prkdcscid/J",
"Tumor Prep":"tumor solid",
"Engraftment Site":"Sub-cutaneous;  dorsal flank"
},
{"Patient ID":"WUSTL 343",
"Gender":"M",
"Age":"67",
"Model ID":"WUSTL 343-06",
"Primary Site":"Head of the Pancreas",
"Sample Site":"Pancreas",
"Tumor Type":"Primary",
"Sample Type":"surgical sample",
"Histology":"Pancreatic Ductal Adenocarcinoma",
"Clinical Diagnosis":"Pancreatic Ductal Adenocarcinoma",
"Grades":"G2/G3",
"Stage":"pT3/N1/MX",
"Markers":"",
"Treatment Naive":"Not Specified",
"Strain":"NOD.CB17-Prkdcscid/J",
"Tumor Prep":"tumor solid",
"Engraftment Site":"Sub-cutaneous;  dorsal flank"
},
{"Patient ID":"WUSTL 343",
"Gender":"M",
"Age":"67",
"Model ID":"WUSTL 343-07",
"Primary Site":"Head of the Pancreas",
"Sample Site":"Lymph Node",
"Tumor Type":"Metastatic",
"Sample Type":"surgical sample",
"Histology":"Pancreatic Ductal Adenocarcinoma",
"Clinical Diagnosis":"Pancreatic Ductal Adenocarcinoma",
"Grades":"G2/G3",
"Stage":"pT1/N1/MX",
"Markers":"",
"Treatment Naive":"Not Specified",
"Strain":"NOD.CB17-Prkdcscid/J",
"Tumor Prep":"tumor solid",
"Engraftment Site":"Sub-cutaneous;  dorsal flank"
},
{"Patient ID":"WUSTL 345",
"Gender":"F",
"Age":"61",
"Model ID":"WUSTL 345-06",
"Primary Site":"Colon",
"Sample Site":"Colon",
"Tumor Type":"Primary",
"Sample Type":"surgical sample",
"Histology":"Colorectal Adenocarcinoma",
"Clinical Diagnosis":"Colorectal Adenocarcinoma",
"Grades":"G2",
"Stage":"pT3/N1a/MX",
"Markers":"",
"Treatment Naive":"Not Specified",
"Strain":"NOD.CB17-Prkdcscid/J",
"Tumor Prep":"tumor solid",
"Engraftment Site":"Sub-cutaneous;  dorsal flank"
},
{"Patient ID":"WUSTL 349",
"Gender":"M",
"Age":"54",
"Model ID":"WUSTL 349-06",
"Primary Site":"Colon",
"Sample Site":"Colon",
"Tumor Type":"Primary",
"Sample Type":"surgical sample",
"Histology":"Colorectal Adenocarcinoma",
"Clinical Diagnosis":"Colorectal Adenocarcinoma",
"Grades":"G2",
"Stage":"ypT2/N1b/M1a",
"Markers":"",
"Treatment Naive":"Not Specified",
"Strain":"NOD.CB17-Prkdcscid/J",
"Tumor Prep":"tumor solid",
"Engraftment Site":"Sub-cutaneous;  dorsal flank"
},
{"Patient ID":"WUSTL 354",
"Gender":"F",
"Age":"39",
"Model ID":"WUSTL 354-07",
"Primary Site":"Colon",
"Sample Site":"Liver",
"Tumor Type":"Metastatic",
"Sample Type":"surgical sample",
"Histology":"Colorectal Adenocarcinoma",
"Clinical Diagnosis":"Colorectal Adenocarcinoma",
"Grades":"Not Specified",
"Stage":"Not Specified",
"Markers":"",
"Treatment Naive":"Not Specified",
"Strain":"NOD.CB17-Prkdcscid/J",
"Tumor Prep":"tumor solid",
"Engraftment Site":"Sub-cutaneous;  dorsal flank"
},
{"Patient ID":"WUSTL 356 [2]",
"Gender":"M",
"Age":"55",
"Model ID":"WUSTL 356 [2]-07",
"Primary Site":"Colon",
"Sample Site":"Lung",
"Tumor Type":"Metastatic",
"Sample Type":"surgical sample",
"Histology":"Colorectal Adenocarcinoma",
"Clinical Diagnosis":"Colorectal Adenocarcinoma",
"Grades":"Not Specified",
"Stage":"Not Specified",
"Markers":"",
"Treatment Naive":"Not Specified",
"Strain":"NOD.CB17-Prkdcscid/J",
"Tumor Prep":"tumor solid",
"Engraftment Site":"Sub-cutaneous;  dorsal flank"
},
{"Patient ID":"WUSTL 369",
"Gender":"M",
"Age":"82",
"Model ID":"WUSTL 369-06",
"Primary Site":"Colon",
"Sample Site":"Colon",
"Tumor Type":"Primary",
"Sample Type":"surgical sample",
"Histology":"Colorectal Adenocarcinoma",
"Clinical Diagnosis":"Colorectal Adenocarcinoma",
"Grades":"G2",
"Stage":"pT3/N0/MX",
"Markers":"",
"Treatment Naive":"Not Specified",
"Strain":"NOD.CB17-Prkdcscid/J",
"Tumor Prep":"tumor solid",
"Engraftment Site":"Sub-cutaneous;  dorsal flank"
},
{"Patient ID":"WUSTL 374",
"Gender":"M",
"Age":"46",
"Model ID":"WUSTL 374-06",
"Primary Site":"Colon",
"Sample Site":"Colon",
"Tumor Type":"Primary",
"Sample Type":"surgical sample",
"Histology":"Colorectal Adenocarcinoma",
"Clinical Diagnosis":"Colorectal Adenocarcinoma",
"Grades":"G2/G3",
"Stage":"pT3/N2b/MX",
"Markers":"",
"Treatment Naive":"Not Specified",
"Strain":"NOD.CB17-Prkdcscid/J",
"Tumor Prep":"tumor solid",
"Engraftment Site":"Sub-cutaneous;  dorsal flank"
},
{"Patient ID":"WUSTL 393",
"Gender":"M",
"Age":"49",
"Model ID":"WUSTL 393-06",
"Primary Site":"Rectosigmoid Colon",
"Sample Site":"Colon",
"Tumor Type":"Primary",
"Sample Type":"surgical sample",
"Histology":"Colorectal Adenocarcinoma",
"Clinical Diagnosis":"Colorectal Adenocarcinoma",
"Grades":"G2",
"Stage":"pT3/N0/MX",
"Markers":"",
"Treatment Naive":"Not Specified",
"Strain":"NOD.CB17-Prkdcscid/J",
"Tumor Prep":"tumor solid",
"Engraftment Site":"Sub-cutaneous;  dorsal flank"
},
{"Patient ID":"WUSTL 394",
"Gender":"M",
"Age":"62",
"Model ID":"WUSTL 394-06",
"Primary Site":"Head of the Pancreas",
"Sample Site":"Pancreas",
"Tumor Type":"Primary",
"Sample Type":"surgical sample",
"Histology":"Pancreatic Ductal Adenocarcinoma",
"Clinical Diagnosis":"Pancreatic Ductal Adenocarcinoma",
"Grades":"G2/G3",
"Stage":"pT3/N1/MX",
"Markers":"",
"Treatment Naive":"Not Specified",
"Strain":"NOD.CB17-Prkdcscid/J",
"Tumor Prep":"tumor solid",
"Engraftment Site":"Sub-cutaneous;  dorsal flank"
},
{"Patient ID":"WUSTL 397",
"Gender":"M",
"Age":"76",
"Model ID":"WUSTL 397-06",
"Primary Site":"Colon",
"Sample Site":"Colon",
"Tumor Type":"Primary",
"Sample Type":"surgical sample",
"Histology":"Colorectal Adenocarcinoma",
"Clinical Diagnosis":"Colorectal Adenocarcinoma",
"Grades":"G2",
"Stage":"pT2/N1a/M1a",
"Markers":"",
"Treatment Naive":"Not Specified",
"Strain":"NOD.CB17-Prkdcscid/J",
"Tumor Prep":"tumor solid",
"Engraftment Site":"Sub-cutaneous;  dorsal flank"
},
{"Patient ID":"WUSTL 402",
"Gender":"F",
"Age":"41",
"Model ID":"WUSTL 402-06",
"Primary Site":"Head of the Pancreas",
"Sample Site":"Pancreas",
"Tumor Type":"Primary",
"Sample Type":"surgical sample",
"Histology":"Pancreatic Ductal Adenocarcinoma",
"Clinical Diagnosis":"Pancreatic Ductal Adenocarcinoma",
"Grades":"G2",
"Stage":"pT2/N0/MX",
"Markers":"",
"Treatment Naive":"Not Specified",
"Strain":"NOD.CB17-Prkdcscid/J",
"Tumor Prep":"tumor solid",
"Engraftment Site":"Sub-cutaneous;  dorsal flank"
},
{"Patient ID":"WUSTL 432",
"Gender":"M",
"Age":"51",
"Model ID":"WUSTL 432-06",
"Primary Site":"Head of the Pancreas",
"Sample Site":"Pancreas",
"Tumor Type":"Primary",
"Sample Type":"surgical sample",
"Histology":"Pancreatic Ductal Adenocarcinoma",
"Clinical Diagnosis":"Pancreatic Ductal Adenocarcinoma",
"Grades":"GX",
"Stage":"ypT3/N1/MX",
"Markers":"",
"Treatment Naive":"Not Specified",
"Strain":"NOD.CB17-Prkdcscid/J",
"Tumor Prep":"tumor solid",
"Engraftment Site":"Sub-cutaneous;  dorsal flank"
},
{"Patient ID":"WUSTL 440",
"Gender":"M",
"Age":"78",
"Model ID":"WUSTL 440-06",
"Primary Site":"Tail of the Pancreas",
"Sample Site":"Pancreas",
"Tumor Type":"Primary",
"Sample Type":"surgical sample",
"Histology":"Pancreatic Ductal Adenocarcinoma",
"Clinical Diagnosis":"Pancreatic Ductal Adenocarcinoma",
"Grades":"G2/G3",
"Stage":"pT3/N1/MX",
"Markers":"",
"Treatment Naive":"Not Specified",
"Strain":"NOD.CB17-Prkdcscid/J",
"Tumor Prep":"tumor solid",
"Engraftment Site":"Sub-cutaneous;  dorsal flank"
},
{"Patient ID":"WUSTL 445",
"Gender":"F",
"Age":"60",
"Model ID":"WUSTL 445-07",
"Primary Site":"Colon",
"Sample Site":"Liver",
"Tumor Type":"Metastatic",
"Sample Type":"surgical sample",
"Histology":"Colorectal Adenocarcinoma",
"Clinical Diagnosis":"Colorectal Adenocarcinoma",
"Grades":"G2",
"Stage":"ypT2/N0/M1a",
"Markers":"",
"Treatment Naive":"Not Specified",
"Strain":"NOD.CB17-Prkdcscid/J",
"Tumor Prep":"tumor solid",
"Engraftment Site":"Sub-cutaneous;  dorsal flank"
},
{"Patient ID":"WUSTL 45",
"Gender":"M",
"Age":"58",
"Model ID":"WUSTL 45-07",
"Primary Site":"Colon",
"Sample Site":"Liver",
"Tumor Type":"Metastatic",
"Sample Type":"surgical sample",
"Histology":"Colorectal Adenocarcinoma",
"Clinical Diagnosis":"Colorectal Adenocarcinoma",
"Grades":"Not Specified",
"Stage":"Not Specified",
"Markers":"",
"Treatment Naive":"Not Specified",
"Strain":"NOD.CB17-Prkdcscid/J",
"Tumor Prep":"tumor solid",
"Engraftment Site":"Sub-cutaneous;  dorsal flank"
},
{"Patient ID":"WUSTL 459",
"Gender":"M",
"Age":"72",
"Model ID":"WUSTL 459-9",
"Primary Site":"Pancreas",
"Sample Site":"Lymph Node",
"Tumor Type":"Metastatic",
"Sample Type":"surgical sample",
"Histology":"Pancreatic Neuroendocrine Carcinoma",
"Clinical Diagnosis":"Pancreatic Neuroendocrine Carcinoma",
"Grades":"G2",
"Stage":"pT3/N1/M1",
"Markers":"",
"Treatment Naive":"Not Specified",
"Strain":"NOD.CB17-Prkdcscid/J",
"Tumor Prep":"tumor solid",
"Engraftment Site":"Sub-cutaneous;  dorsal flank"
},
{"Patient ID":"WUSTL 459",
"Gender":"M",
"Age":"72",
"Model ID":"WUSTL 459-10",
"Primary Site":"Pancreas",
"Sample Site":"Liver",
"Tumor Type":"Metastatic",
"Sample Type":"surgical sample",
"Histology":"Pancreatic Neuroendocrine Carcinoma",
"Clinical Diagnosis":"Pancreatic Neuroendocrine Carcinoma",
"Grades":"G2",
"Stage":"pT3/N1/M1",
"Markers":"",
"Treatment Naive":"Not Specified",
"Strain":"NOD.CB17-Prkdcscid/J",
"Tumor Prep":"tumor solid",
"Engraftment Site":"Sub-cutaneous;  dorsal flank"
},
{"Patient ID":"WUSTL 465",
"Gender":"F",
"Age":"67",
"Model ID":"WUSTL 465-06",
"Primary Site":"Rectum",
"Sample Site":"Rectum",
"Tumor Type":"Primary",
"Sample Type":"surgical sample",
"Histology":"Colorectal Adenocarcinoma",
"Clinical Diagnosis":"Colorectal Adenocarcinoma",
"Grades":"G3",
"Stage":"pT4b/N1c/M0",
"Markers":"",
"Treatment Naive":"Not Specified",
"Strain":"NOD.CB17-Prkdcscid/J",
"Tumor Prep":"tumor solid",
"Engraftment Site":"Sub-cutaneous;  dorsal flank"
},
{"Patient ID":"WUSTL 470",
"Gender":"F",
"Age":"82",
"Model ID":"WUSTL 470-07",
"Primary Site":"Colon",
"Sample Site":"Liver",
"Tumor Type":"Metastatic",
"Sample Type":"surgical sample",
"Histology":"Colorectal Adenocarcinoma",
"Clinical Diagnosis":"Colorectal Adenocarcinoma",
"Grades":"Not Specified",
"Stage":"Not Specified",
"Markers":"",
"Treatment Naive":"Not Specified",
"Strain":"NOD.CB17-Prkdcscid/J",
"Tumor Prep":"tumor solid",
"Engraftment Site":"Sub-cutaneous;  dorsal flank"
},
{"Patient ID":"WUSTL 478",
"Gender":"M",
"Age":"48",
"Model ID":"WUSTL 478-07",
"Primary Site":"Colon",
"Sample Site":"Lung",
"Tumor Type":"Metastatic",
"Sample Type":"surgical sample",
"Histology":"Colorectal Adenocarcinoma",
"Clinical Diagnosis":"Colorectal Adenocarcinoma",
"Grades":"Not Specified",
"Stage":"Not Specified",
"Markers":"",
"Treatment Naive":"Not Specified",
"Strain":"NOD.CB17-Prkdcscid/J",
"Tumor Prep":"tumor solid",
"Engraftment Site":"Sub-cutaneous;  dorsal flank"
},
{"Patient ID":"WUSTL 516",
"Gender":"F",
"Age":"63",
"Model ID":"WUSTL 516-07",
"Primary Site":"Colon",
"Sample Site":"Liver",
"Tumor Type":"Metastatic",
"Sample Type":"surgical sample",
"Histology":"Colorectal Adenocarcinoma",
"Clinical Diagnosis":"Colorectal Adenocarcinoma",
"Grades":"Not Specified",
"Stage":"Not Specified",
"Markers":"",
"Treatment Naive":"Not Specified",
"Strain":"NOD.CB17-Prkdcscid/J",
"Tumor Prep":"tumor solid",
"Engraftment Site":"Sub-cutaneous;  dorsal flank"
},
{"Patient ID":"WUSTL 655",
"Gender":"F",
"Age":"43",
"Model ID":"WUSTL 655-06",
"Primary Site":"Colon",
"Sample Site":"Colon",
"Tumor Type":"Primary",
"Sample Type":"surgical sample",
"Histology":"Colorectal Adenocarcinoma",
"Clinical Diagnosis":"Colorectal Adenocarcinoma",
"Grades":"G2",
"Stage":"pT3/N1/M1a",
"Markers":"",
"Treatment Naive":"Not Specified",
"Strain":"NOD.CB17-Prkdcscid/J",
"Tumor Prep":"tumor solid",
"Engraftment Site":"Sub-cutaneous;  dorsal flank"
},
{"Patient ID":"WUSTL 655",
"Gender":"F",
"Age":"43",
"Model ID":"WUSTL 655-08",
"Primary Site":"Colon",
"Sample Site":"Liver",
"Tumor Type":"Metastatic",
"Sample Type":"surgical sample",
"Histology":"Colorectal Adenocarcinoma",
"Clinical Diagnosis":"Colorectal Adenocarcinoma",
"Grades":"G2",
"Stage":"pT3/N1/M1a",
"Markers":"",
"Treatment Naive":"Not Specified",
"Strain":"NOD.CB17-Prkdcscid/J",
"Tumor Prep":"tumor solid",
"Engraftment Site":"Sub-cutaneous;  dorsal flank"
},
{"Patient ID":"WUSTL 658",
"Gender":"F",
"Age":"46",
"Model ID":"WUSTL 658-07",
"Primary Site":"Skin",
"Sample Site":"Skeletal Muscle",
"Tumor Type":"Metastatic",
"Sample Type":"surgical sample",
"Histology":"Cutaneous Melanoma",
"Clinical Diagnosis":"Cutaneous Melanoma",
"Grades":"Not Specified",
"Stage":"pN1",
"Markers":"",
"Treatment Naive":"Not Specified",
"Strain":"NOD.CB17-Prkdcscid/J",
"Tumor Prep":"tumor solid",
"Engraftment Site":"Sub-cutaneous;  dorsal flank"
},
{"Patient ID":"WUSTL 658",
"Gender":"F",
"Age":"46",
"Model ID":"WUSTL 658-09",
"Primary Site":"Skin",
"Sample Site":"Adrenal Gland",
"Tumor Type":"Metastatic",
"Sample Type":"surgical sample",
"Histology":"Cutaneous Melanoma",
"Clinical Diagnosis":"Cutaneous Melanoma",
"Grades":"Not Specified",
"Stage":"pN1",
"Markers":"",
"Treatment Naive":"Not Specified",
"Strain":"NOD.CB17-Prkdcscid/J",
"Tumor Prep":"tumor solid",
"Engraftment Site":"Sub-cutaneous;  dorsal flank"
},
{"Patient ID":"WUSTL 669",
"Gender":"M",
"Age":"70",
"Model ID":"WUSTL 669-07",
"Primary Site":"Skin",
"Sample Site":"Lymph Node",
"Tumor Type":"Metastatic",
"Sample Type":"surgical sample",
"Histology":"Cutaneous Melanoma",
"Clinical Diagnosis":"Cutaneous Melanoma",
"Grades":"Not Specified",
"Stage":"pN2",
"Markers":"",
"Treatment Naive":"Not Specified",
"Strain":"NOD.CB17-Prkdcscid/J",
"Tumor Prep":"tumor solid",
"Engraftment Site":"Sub-cutaneous;  dorsal flank"
},
{"Patient ID":"WUSTL 674",
"Gender":"M",
"Age":"52",
"Model ID":"WUSTL 674-07",
"Primary Site":"Skin",
"Sample Site":"Lymph Node",
"Tumor Type":"Metastatic",
"Sample Type":"surgical sample",
"Histology":"Cutaneous Melanoma",
"Clinical Diagnosis":"Cutaneous Melanoma",
"Grades":"Not Specified",
"Stage":"pN2/MX",
"Markers":"",
"Treatment Naive":"Not Specified",
"Strain":"NOD.CB17-Prkdcscid/J",
"Tumor Prep":"tumor solid",
"Engraftment Site":"Sub-cutaneous;  dorsal flank"
},
{"Patient ID":"WUSTL 73",
"Gender":"F",
"Age":"52",
"Model ID":"WUSTL 73-07",
"Primary Site":"Colon",
"Sample Site":"Liver",
"Tumor Type":"Metastatic",
"Sample Type":"surgical sample",
"Histology":"Colorectal Adenocarcinoma",
"Clinical Diagnosis":"Colorectal Adenocarcinoma",
"Grades":"Not Specified",
"Stage":"Not Specified",
"Markers":"",
"Treatment Naive":"Not Specified",
"Strain":"NOD.CB17-Prkdcscid/J",
"Tumor Prep":"tumor solid",
"Engraftment Site":"Sub-cutaneous;  dorsal flank"
},
{"Patient ID":"WUSTL 738",
"Gender":"M",
"Age":"57",
"Model ID":"WUSTL 738-07",
"Primary Site":"Adrenal gland",
"Sample Site":"Adrenal gland",
"Tumor Type":"Metastatic",
"Sample Type":"surgical sample",
"Histology":"Melanoma",
"Clinical Diagnosis":"Melanoma",
"Grades":"Not Specified",
"Stage":"pN1",
"Markers":"",
"Treatment Naive":"Not Specified",
"Strain":"NOD.CB17-Prkdcscid/J",
"Tumor Prep":"tumor solid",
"Engraftment Site":"Sub-cutaneous;  dorsal flank"
},
{"Patient ID":"WUSTL 739",
"Gender":"F",
"Age":"55",
"Model ID":"WUSTL 739-07",
"Primary Site":"Small Intestine",
"Sample Site":"Small Intestine",
"Tumor Type":"Primary",
"Sample Type":"surgical sample",
"Histology":"Melanoma",
"Clinical Diagnosis":"Melanoma",
"Grades":"Not Specified",
"Stage":"Not Specified",
"Markers":"",
"Treatment Naive":"Not Specified",
"Strain":"NOD.CB17-Prkdcscid/J",
"Tumor Prep":"tumor solid",
"Engraftment Site":"Sub-cutaneous;  dorsal flank"
},
{"Patient ID":"WUSTL 745",
"Gender":"M",
"Age":"56",
"Model ID":"WUSTL 745-07",
"Primary Site":"Colon",
"Sample Site":"Liver",
"Tumor Type":"Metastatic",
"Sample Type":"surgical sample",
"Histology":"Colorectal Adenocarcinoma",
"Clinical Diagnosis":"Colorectal Adenocarcinoma",
"Grades":"G3",
"Stage":"ypT3/N1a/MX",
"Markers":"",
"Treatment Naive":"Not Specified",
"Strain":"NOD.CB17-Prkdcscid/J",
"Tumor Prep":"tumor solid",
"Engraftment Site":"Sub-cutaneous;  dorsal flank"
},
{"Patient ID":"WUSTL 803",
"Gender":"F",
"Age":"49",
"Model ID":"WUSTL 803-07",
"Primary Site":"Pancreas",
"Sample Site":"Umbilicus",
"Tumor Type":"Metastatic",
"Sample Type":"biopsy",
"Histology":"Pancreatic Ductal Adenocarcinoma",
"Clinical Diagnosis":"Pancreatic Ductal Adenocarcinoma",
"Grades":"Not Specified",
"Stage":"Not Specified",
"Markers":"",
"Treatment Naive":"Not Specified",
"Strain":"NOD.CB17-Prkdcscid/J",
"Tumor Prep":"tumor solid",
"Engraftment Site":"Sub-cutaneous;  dorsal flank"
},
{"Patient ID":"WUSTL 822",
"Gender":"M",
"Age":"85",
"Model ID":"WUSTL 822-07",
"Primary Site":"Colon",
"Sample Site":"Liver",
"Tumor Type":"Metastatic",
"Sample Type":"surgical sample",
"Histology":"Colorectal Adenocarcinoma",
"Clinical Diagnosis":"Colorectal Adenocarcinoma",
"Grades":"Not Specified",
"Stage":"Not Specified",
"Markers":"",
"Treatment Naive":"Not Specified",
"Strain":"NOD.CB17-Prkdcscid/J",
"Tumor Prep":"tumor solid",
"Engraftment Site":"Sub-cutaneous;  dorsal flank"
},
{"Patient ID":"WUSTL 84",
"Gender":"M",
"Age":"73",
"Model ID":"WUSTL 84-07",
"Primary Site":"Colon",
"Sample Site":"Liver",
"Tumor Type":"Metastatic",
"Sample Type":"surgical sample",
"Histology":"Colorectal Adenocarcinoma",
"Clinical Diagnosis":"Colorectal Adenocarcinoma",
"Grades":"Not Specified",
"Stage":"Not Specified",
"Markers":"",
"Treatment Naive":"Not Specified",
"Strain":"NOD.CB17-Prkdcscid/J",
"Tumor Prep":"tumor solid",
"Engraftment Site":"Sub-cutaneous;  dorsal flank"
},
{"Patient ID":"WUSTL 845",
"Gender":"M",
"Age":"63",
"Model ID":"WUSTL 845-07",
"Primary Site":"Colon",
"Sample Site":"Liver",
"Tumor Type":"Metastatic",
"Sample Type":"surgical sample",
"Histology":"Colorectal Adenocarcinoma",
"Clinical Diagnosis":"Colorectal Adenocarcinoma",
"Grades":"Not Specified",
"Stage":"Not Specified",
"Markers":"",
"Treatment Naive":"Not Specified",
"Strain":"NOD.CB17-Prkdcscid/J",
"Tumor Prep":"tumor solid",
"Engraftment Site":"Sub-cutaneous;  dorsal flank"
},
{"Patient ID":"WUSTL 881",
"Gender":"M",
"Age":"69",
"Model ID":"WUSTL 881-06",
"Primary Site":"Tail of the Pancreas",
"Sample Site":"Pancreas",
"Tumor Type":"Primary",
"Sample Type":"surgical sample",
"Histology":"Adenocarcinoma",
"Clinical Diagnosis":"Adenocarcinoma",
"Grades":"G2",
"Stage":"pT3/N0/M0",
"Markers":"",
"Treatment Naive":"Not Specified",
"Strain":"NOD.CB17-Prkdcscid/J",
"Tumor Prep":"tumor solid",
"Engraftment Site":"Sub-cutaneous;  dorsal flank"
},
{"Patient ID":"WUSTL 911",
"Gender":"F",
"Age":"32",
"Model ID":"WUSTL 911-06",
"Primary Site":"Colon",
"Sample Site":"Colon",
"Tumor Type":"Primary",
"Sample Type":"surgical sample",
"Histology":"Colorectal Adenocarcinoma",
"Clinical Diagnosis":"Colorectal Adenocarcinoma",
"Grades":"G1/G2",
"Stage":"ypT3/N1b/M1a",
"Markers":"",
"Treatment Naive":"Not Specified",
"Strain":"NOD.CB17-Prkdcscid/J",
"Tumor Prep":"tumor solid",
"Engraftment Site":"Sub-cutaneous;  dorsal flank"
},
{"Patient ID":"WUSTL 911",
"Gender":"F",
"Age":"32",
"Model ID":"WUSTL 911-07",
"Primary Site":"Colon",
"Sample Site":"Liver",
"Tumor Type":"Metastatic",
"Sample Type":"surgical sample",
"Histology":"Colorectal Adenocarcinoma",
"Clinical Diagnosis":"Colorectal Adenocarcinoma",
"Grades":"Not Specified",
"Stage":"Not Specified",
"Markers":"",
"Treatment Naive":"Not Specified",
"Strain":"NOD.CB17-Prkdcscid/J",
"Tumor Prep":"tumor solid",
"Engraftment Site":"Sub-cutaneous;  dorsal flank"
},
{"Patient ID":"WUSTL 95",
"Gender":"M",
"Age":"41",
"Model ID":"WUSTL 95-07",
"Primary Site":"Colon",
"Sample Site":"Liver",
"Tumor Type":"Metastatic",
"Sample Type":"surgical sample",
"Histology":"Colorectal Adenocarcinoma",
"Clinical Diagnosis":"Colorectal Adenocarcinoma",
"Grades":"G3",
"Stage":"ypT4b/N1b/M1",
"Markers":"",
"Treatment Naive":"Not Specified",
"Strain":"NOD.CB17-Prkdcscid/J",
"Tumor Prep":"tumor solid",
"Engraftment Site":"Sub-cutaneous;  dorsal flank"
},
{"Patient ID":"WUSTL 978",
"Gender":"F",
"Age":"43",
"Model ID":"WUSTL 978-07",
"Primary Site":"Skin",
"Sample Site":"Lymph Node",
"Tumor Type":"Metastatic",
"Sample Type":"surgical sample",
"Histology":"Cutaneous Melanoma",
"Clinical Diagnosis":"Cutaneous Melanoma",
"Grades":"Not Specified",
"Stage":"Not Specified",
"Markers":"",
"Treatment Naive":"Not Specified",
"Strain":"NOD.CB17-Prkdcscid/J",
"Tumor Prep":"tumor solid",
"Engraftment Site":"Sub-cutaneous;  dorsal flank"
}]}